{
  "restaurant_info": {
    "id": "150519",
    "name": "Bulbul Alsaadah",
    "region": "Abha",
    "state": "Abha",
    "country": "Saudi Arabia",
    "coordinates": {
      "latitude": 18.25823464382052,
      "longitude": 42.59406220000002
    },
    "rating": 3.8,
    "review_count": 20,
    "type_of_food": "Fast Food,Juices",
    "hungerstation_url": "https://hungerstation.com/sa-en/restaurants/abha/al-arin/150519"
  },
  "menu_categories": {
    "Bestsellers 🔥": [
      {
        "item_en": "Special Chicken Pizza - Medium",
        "item_ar": "Special Chicken Pizza - Medium",
        "price": 23,
        "currency": "SAR",
        "description": "",
        "image": "",
        "offer_price": null,
        "discount": "",
        "menu_id": 70111957
      },
      {
        "item_en": "Ash Albulbul - Small",
        "item_ar": "Ash Albulbul - Small",
        "price": 16,
        "currency": "SAR",
        "description": "",
        "image": "",
        "offer_price": null,
        "discount": "",
        "menu_id": 70111950
      },
      {
        "item_en": "Ash Albulbul - Medium",
        "item_ar": "Ash Albulbul - Medium",
        "price": 22,
        "currency": "SAR",
        "description": "",
        "image": "",
        "offer_price": null,
        "discount": "",
        "menu_id": 70111951
      },
      {
        "item_en": "Regular Vegetable Pizza - Small",
        "item_ar": "Regular Vegetable Pizza - Small",
        "price": 17,
        "currency": "SAR",
        "description": "",
        "image": "",
        "offer_price": null,
        "discount": "",
        "menu_id": 70111908
      }
    ],
    "Broasted": [
      {
        "item_en": "French Fries - Small",
        "item_ar": "French Fries - Small",
        "price": 12,
        "currency": "SAR",
        "description": "Crispy french fries prepared in a delicious way.",
        "image": "https://images.deliveryhero.io/image/hungerstation/product/image_url_ref/334d4708d177b6736e01137e168c617b.jpeg?width=1920",
        "offer_price": null,
        "discount": "",
        "menu_id": 70111967
      },
      {
        "item_en": "French Fries - Medium",
        "item_ar": "French Fries - Medium",
        "price": 17,
        "currency": "SAR",
        "description": "Crispy french fries prepared in a delicious way.",
        "image": "https://images.deliveryhero.io/image/hungerstation/product/image_url_ref/334d4708d177b6736e01137e168c617b.jpeg?width=1920",
        "offer_price": null,
        "discount": "",
        "menu_id": 70111968
      },
      {
        "item_en": "French Fries - Large",
        "item_ar": "French Fries - Large",
        "price": 23,
        "currency": "SAR",
        "description": "Crispy french fries prepared in a delicious way.",
        "image": "https://images.deliveryhero.io/image/hungerstation/product/image_url_ref/334d4708d177b6736e01137e168c617b.jpeg?width=1920",
        "offer_price": null,
        "discount": "",
        "menu_id": 70111969
      }
    ],
    "Pies": [
      {
        "item_en": "Labneh And Thyme",
        "item_ar": "Labneh And Thyme",
        "price": 6,
        "currency": "SAR",
        "description": "A pie filled with fresh labneh with a distinctive thyme flavor",
        "image": "https://images.deliveryhero.io/image/hungerstation/menuitem/image_url_ref/ea9b000397d50e078575beaf0e44d7ac.jpeg?width=222",
        "offer_price": null,
        "discount": "",
        "menu_id": 70111888
      },
      {
        "item_en": "Tuna",
        "item_ar": "Tuna",
        "price": 6,
        "currency": "SAR",
        "description": "A delicious pie filled with tuna",
        "image": "",
        "offer_price": null,
        "discount": "",
        "menu_id": 70111889
      },
      {
        "item_en": "Sausage Cheese",
        "item_ar": "Sausage Cheese",
        "price": 6,
        "currency": "SAR",
        "description": "A delicious pie filled with cheese and delicious sausage pieces",
        "image": "https://images.deliveryhero.io/image/global-menu-service/HS_SA/vendor/150519/PRODUCT/70111890/6fd82699-baef-4064-8bb9-2695ad79346f.jpg?width=222",
        "offer_price": null,
        "discount": "",
        "menu_id": 70111890
      },
      {
        "item_en": "Falafel Pie",
        "item_ar": "Falafel Pie",
        "price": 6,
        "currency": "SAR",
        "description": "Delicious fluffy pastry containing crispy fried falafel balls.",
        "image": "https://images.deliveryhero.io/image/global-menu-service/HS_SA/vendor/150519/PRODUCT/70111894/ec1a4bd8-2945-4828-b7b2-a0990252552e.jpg?width=222",
        "offer_price": null,
        "discount": "",
        "menu_id": 70111894
      },
      {
        "item_en": "Egg And Cheese",
        "item_ar": "Egg And Cheese",
        "price": 6,
        "currency": "SAR",
        "description": "Pies stuffed with a mixture of eggs and cheese, giving a rich and nutritious taste.",
        "image": "https://images.deliveryhero.io/image/global-menu-service/HS_SA/vendor/150519/PRODUCT/70111895/bcacbcc6-71fd-490b-9799-3db49bb9dc06.jpg?width=222",
        "offer_price": null,
        "discount": "",
        "menu_id": 70111895
      },
      {
        "item_en": "Labneh",
        "item_ar": "Labneh",
        "price": 6,
        "currency": "SAR",
        "description": "Pies stuffed with fresh labneh, giving a distinctive flavor and delicious taste.",
        "image": "https://images.deliveryhero.io/image/global-menu-service/HS_SA/vendor/150519/PRODUCT/70111896/dc66eff1-3756-4a97-b5d9-ffc17cde9915.jpg?width=222",
        "offer_price": null,
        "discount": "",
        "menu_id": 70111896
      },
      {
        "item_en": "Cream Cheese",
        "item_ar": "Cream Cheese",
        "price": 6,
        "currency": "SAR",
        "description": "Pies stuffed with cream cheese , characterized by their soft texture.",
        "image": "https://images.deliveryhero.io/image/global-menu-service/HS_SA/vendor/150519/PRODUCT/70111897/1e7337f2-cd8d-43a6-a846-2e7b0f0d5532.jpg?width=222",
        "offer_price": null,
        "discount": "",
        "menu_id": 70111897
      },
      {
        "item_en": "Cheddar Cheese",
        "item_ar": "Cheddar Cheese",
        "price": 6,
        "currency": "SAR",
        "description": "Pies stuffed with cheddar cheese and baked in the oven.",
        "image": "https://images.deliveryhero.io/image/global-menu-service/HS_SA/vendor/150519/PRODUCT/70111898/7936f535-afb6-464e-bfd6-48064f369cfc.jpg?width=222",
        "offer_price": null,
        "discount": "",
        "menu_id": 70111898
      },
      {
        "item_en": "Chicken",
        "item_ar": "Chicken",
        "price": 6,
        "currency": "SAR",
        "description": "Pies stuffed with chicken pieces and spices, giving the pies a strong and rich flavor.",
        "image": "https://images.deliveryhero.io/image/hungerstation/menuitem/image_url_ref/18ba0a52999491bac4739a26bb089fbd.jpeg?width=222",
        "offer_price": null,
        "discount": "",
        "menu_id": 70111901
      },
      {
        "item_en": "Thyme",
        "item_ar": "Thyme",
        "price": 6,
        "currency": "SAR",
        "description": "Delicious fluffy pastry stuffed with thyme.",
        "image": "https://images.deliveryhero.io/image/global-menu-service/HS_SA/vendor/150519/PRODUCT/70111902/7c733eba-b040-4a34-951e-2077808ef1a8.jpg?width=222",
        "offer_price": null,
        "discount": "",
        "menu_id": 70111902
      },
      {
        "item_en": "Spinach",
        "item_ar": "Spinach",
        "price": 6,
        "currency": "SAR",
        "description": "Delicious fluffy pastry stuffed with spinach and baked in the oven.",
        "image": "https://images.deliveryhero.io/image/global-menu-service/HS_SA/vendor/150519/PRODUCT/70111903/00fbc63f-37bf-41bb-8dca-403ed98201a8.jpg?width=222",
        "offer_price": null,
        "discount": "",
        "menu_id": 70111903
      },
      {
        "item_en": "Plain Eggs",
        "item_ar": "Plain Eggs",
        "price": 6,
        "currency": "SAR",
        "description": "Pies stuffed with eggs, offering a simple and nutritious taste.",
        "image": "https://images.deliveryhero.io/image/hungerstation/menuitem/image_url_ref/97091a69fb7380772af9c2ed9ad1cea4.jpeg?width=222",
        "offer_price": null,
        "discount": "",
        "menu_id": 70111904
      },
      {
        "item_en": "Mixed Plate - Small",
        "item_ar": "Mixed Plate - Small",
        "price": 22,
        "currency": "SAR",
        "description": "A plate consisting of several pies with assorted delicious fillings, baked in the oven.",
        "image": "https://images.deliveryhero.io/image/hungerstation/product/image_url_ref/02723c81cc845ba3b5019f816a7600cf.jpeg?width=1920",
        "offer_price": null,
        "discount": "",
        "menu_id": 70111885
      },
      {
        "item_en": "Mixed Plate - Medium",
        "item_ar": "Mixed Plate - Medium",
        "price": 25,
        "currency": "SAR",
        "description": "A plate consisting of several pies with assorted delicious fillings, baked in the oven.",
        "image": "https://images.deliveryhero.io/image/hungerstation/product/image_url_ref/02723c81cc845ba3b5019f816a7600cf.jpeg?width=1920",
        "offer_price": null,
        "discount": "",
        "menu_id": 70111886
      },
      {
        "item_en": "Mixed Plate - Large",
        "item_ar": "Mixed Plate - Large",
        "price": 35,
        "currency": "SAR",
        "description": "A plate consisting of several pies with assorted delicious fillings, baked in the oven.",
        "image": "https://images.deliveryhero.io/image/hungerstation/product/image_url_ref/02723c81cc845ba3b5019f816a7600cf.jpeg?width=1920",
        "offer_price": null,
        "discount": "",
        "menu_id": 70111887
      }
    ],
    "Pizza": [
      {
        "item_en": "Layered Pizza - Small",
        "item_ar": "Layered Pizza - Small",
        "price": 17,
        "currency": "SAR",
        "description": "A pizza rich with multiple layers of cheese, sauce, and a variety of toppings, combining flavors in every bite.",
        "image": "https://images.deliveryhero.io/image/hungerstation/product/image_url_ref/a628f3fa0d763d02312373867dfd3f51.jpeg?width=1920",
        "offer_price": null,
        "discount": "",
        "menu_id": 70111905
      },
      {
        "item_en": "Regular Vegetable Pizza - Small",
        "item_ar": "Regular Vegetable Pizza - Small",
        "price": 17,
        "currency": "SAR",
        "description": "A delicious thin crust pizza topped with a variety of vegetables.",
        "image": "https://images.deliveryhero.io/image/hungerstation/product/image_url_ref/db83a6957aa418f83fa755d89659506f.jpeg?width=1920",
        "offer_price": null,
        "discount": "",
        "menu_id": 70111908
      },
      {
        "item_en": "Regular Sausage Pizza - Small",
        "item_ar": "Regular Sausage Pizza - Small",
        "price": 17,
        "currency": "SAR",
        "description": "A delicious thin crust pizza topped with sausage slices.",
        "image": "https://images.deliveryhero.io/image/hungerstation/product/image_url_ref/60ce8ea8745826c98590ed3b04fd52a3.jpeg?width=1920",
        "offer_price": null,
        "discount": "",
        "menu_id": 70111914
      },
      {
        "item_en": "Tuna Pizza - Small",
        "item_ar": "Tuna Pizza - Small",
        "price": 17,
        "currency": "SAR",
        "description": "Delicious thin crust pizza topped with tuna slices",
        "image": "https://images.deliveryhero.io/image/hungerstation/product/image_url_ref/411de729b71b6f01c9f78252e9021aad.jpeg?width=1920",
        "offer_price": null,
        "discount": "",
        "menu_id": 70111932
      },
      {
        "item_en": "Plain Cheese Pizza - Small",
        "item_ar": "Plain Cheese Pizza - Small",
        "price": 17,
        "currency": "SAR",
        "description": "Delicious thin crust pizza topped with cheese",
        "image": "https://images.deliveryhero.io/image/hungerstation/product/image_url_ref/93daa66809f17f47a70112e78e123286.jpeg?width=1920",
        "offer_price": null,
        "discount": "",
        "menu_id": 70111944
      },
      {
        "item_en": "Ash Albulbul - Small",
        "item_ar": "Ash Albulbul - Small",
        "price": 16,
        "currency": "SAR",
        "description": "Delicious thin crust pizza topped with cheese and honey",
        "image": "https://images.deliveryhero.io/image/hungerstation/product/image_url_ref/62f089438abaac1256951ff534ca1d7c.jpeg?width=1920",
        "offer_price": null,
        "discount": "",
        "menu_id": 70111950
      },
      {
        "item_en": "Chicken Pizza - Small",
        "item_ar": "Chicken Pizza - Small",
        "price": 17,
        "currency": "SAR",
        "description": "Delicious thin crust pizza topped with chicken slices",
        "image": "https://images.deliveryhero.io/image/hungerstation/product/image_url_ref/145360314e36f146c11ac45ef71f6d5a.jpeg?width=1920",
        "offer_price": null,
        "discount": "",
        "menu_id": 70111953
      },
      {
        "item_en": "Special Vegetable Pizza - Small",
        "item_ar": "Special Vegetable Pizza - Small",
        "price": 17,
        "currency": "SAR",
        "description": "A delicious thin crust pizza topped with vegetables and special toppings.",
        "image": "https://images.deliveryhero.io/image/hungerstation/product/image_url_ref/20d7e6d8215fd178831bb8305ac82dde.jpeg?width=1920",
        "offer_price": null,
        "discount": "",
        "menu_id": 70111911
      },
      {
        "item_en": "Special Sausage Pizza - Small",
        "item_ar": "Special Sausage Pizza - Small",
        "price": 18,
        "currency": "SAR",
        "description": "A delicious thin crust pizza topped with sausage slices and special toppings.",
        "image": "https://images.deliveryhero.io/image/hungerstation/product/image_url_ref/0d2db9b53bd17fdbe5708075c8f61d5d.jpeg?width=1920",
        "offer_price": null,
        "discount": "",
        "menu_id": 70111917
      },
      {
        "item_en": "Pepperoni Pizza - Small",
        "item_ar": "Pepperoni Pizza - Small",
        "price": 17,
        "currency": "SAR",
        "description": "A delicious pizza prepared in our own way with pepperoni.",
        "image": "https://images.deliveryhero.io/image/hungerstation/product/image_url_ref/365ca3429d276f14ffede85013498fa4.jpeg?width=1920",
        "offer_price": null,
        "discount": "",
        "menu_id": 70111920
      },
      {
        "item_en": "Special Tuna Pizza - Small",
        "item_ar": "Special Tuna Pizza - Small",
        "price": 19,
        "currency": "SAR",
        "description": "Delicious thin crust pizza topped with tuna slices and special toppings",
        "image": "https://images.deliveryhero.io/image/hungerstation/product/image_url_ref/15acd1ba53f24546beb49cefb690b37a.jpeg?width=1920",
        "offer_price": null,
        "discount": "",
        "menu_id": 70111935
      },
      {
        "item_en": "Special Chicken Pizza - Small",
        "item_ar": "Special Chicken Pizza - Small",
        "price": 17,
        "currency": "SAR",
        "description": "Delicious thin crust pizza topped with chicken slices and special toppings",
        "image": "https://images.deliveryhero.io/image/hungerstation/product/image_url_ref/771821bbff967520442e5ccc6155386e.jpeg?width=1920",
        "offer_price": null,
        "discount": "",
        "menu_id": 70111956
      },
      {
        "item_en": "Regular Vegetable Pizza - Medium",
        "item_ar": "Regular Vegetable Pizza - Medium",
        "price": 22,
        "currency": "SAR",
        "description": "A delicious thin crust pizza topped with a variety of vegetables.",
        "image": "https://images.deliveryhero.io/image/hungerstation/product/image_url_ref/db83a6957aa418f83fa755d89659506f.jpeg?width=1920",
        "offer_price": null,
        "discount": "",
        "menu_id": 70111909
      },
      {
        "item_en": "Regular Sausage Pizza - Medium",
        "item_ar": "Regular Sausage Pizza - Medium",
        "price": 22,
        "currency": "SAR",
        "description": "A delicious thin crust pizza topped with sausage slices.",
        "image": "https://images.deliveryhero.io/image/hungerstation/product/image_url_ref/60ce8ea8745826c98590ed3b04fd52a3.jpeg?width=1920",
        "offer_price": null,
        "discount": "",
        "menu_id": 70111915
      },
      {
        "item_en": "Special Pepperoni Pizza - Small",
        "item_ar": "Special Pepperoni Pizza - Small",
        "price": 20,
        "currency": "SAR",
        "description": "A delicious thin crust pizza topped with meat slices.",
        "image": "https://images.deliveryhero.io/image/hungerstation/product/image_url_ref/31c6f1b61766f52c4509d6359c72e6d4.jpeg?width=1920",
        "offer_price": null,
        "discount": "",
        "menu_id": 70111923
      },
      {
        "item_en": "Tuna Pizza - Medium",
        "item_ar": "Tuna Pizza - Medium",
        "price": 22,
        "currency": "SAR",
        "description": "Delicious thin crust pizza topped with tuna slices",
        "image": "https://images.deliveryhero.io/image/hungerstation/product/image_url_ref/411de729b71b6f01c9f78252e9021aad.jpeg?width=1920",
        "offer_price": null,
        "discount": "",
        "menu_id": 70111933
      },
      {
        "item_en": "Plain Cheese Pizza - Medium",
        "item_ar": "Plain Cheese Pizza - Medium",
        "price": 22,
        "currency": "SAR",
        "description": "Delicious thin crust pizza topped with cheese",
        "image": "https://images.deliveryhero.io/image/hungerstation/product/image_url_ref/93daa66809f17f47a70112e78e123286.jpeg?width=1920",
        "offer_price": null,
        "discount": "",
        "menu_id": 70111945
      },
      {
        "item_en": "Ash Albulbul - Medium",
        "item_ar": "Ash Albulbul - Medium",
        "price": 22,
        "currency": "SAR",
        "description": "Delicious thin crust pizza topped with cheese and honey",
        "image": "https://images.deliveryhero.io/image/hungerstation/product/image_url_ref/62f089438abaac1256951ff534ca1d7c.jpeg?width=1920",
        "offer_price": null,
        "discount": "",
        "menu_id": 70111951
      },
      {
        "item_en": "Chicken Pizza - Medium",
        "item_ar": "Chicken Pizza - Medium",
        "price": 22,
        "currency": "SAR",
        "description": "Delicious thin crust pizza topped with chicken slices",
        "image": "https://images.deliveryhero.io/image/hungerstation/product/image_url_ref/145360314e36f146c11ac45ef71f6d5a.jpeg?width=1920",
        "offer_price": null,
        "discount": "",
        "menu_id": 70111954
      },
      {
        "item_en": "Layered Pizza - Medium",
        "item_ar": "Layered Pizza - Medium",
        "price": 22,
        "currency": "SAR",
        "description": "A pizza rich with multiple layers of cheese, sauce, and a variety of toppings, combining flavors in every bite.",
        "image": "https://images.deliveryhero.io/image/hungerstation/product/image_url_ref/a628f3fa0d763d02312373867dfd3f51.jpeg?width=1920",
        "offer_price": null,
        "discount": "",
        "menu_id": 70111906
      },
      {
        "item_en": "Special Vegetable Pizza - Medium",
        "item_ar": "Special Vegetable Pizza - Medium",
        "price": 23,
        "currency": "SAR",
        "description": "A delicious thin crust pizza topped with vegetables and special toppings.",
        "image": "https://images.deliveryhero.io/image/hungerstation/product/image_url_ref/20d7e6d8215fd178831bb8305ac82dde.jpeg?width=1920",
        "offer_price": null,
        "discount": "",
        "menu_id": 70111912
      },
      {
        "item_en": "Special Sausage Pizza - Medium",
        "item_ar": "Special Sausage Pizza - Medium",
        "price": 24,
        "currency": "SAR",
        "description": "A delicious thin crust pizza topped with sausage slices and special toppings.",
        "image": "https://images.deliveryhero.io/image/hungerstation/product/image_url_ref/0d2db9b53bd17fdbe5708075c8f61d5d.jpeg?width=1920",
        "offer_price": null,
        "discount": "",
        "menu_id": 70111918
      },
      {
        "item_en": "Pepperoni Pizza - Medium",
        "item_ar": "Pepperoni Pizza - Medium",
        "price": 24,
        "currency": "SAR",
        "description": "A delicious pizza prepared in our own way with pepperoni.",
        "image": "https://images.deliveryhero.io/image/hungerstation/product/image_url_ref/365ca3429d276f14ffede85013498fa4.jpeg?width=1920",
        "offer_price": null,
        "discount": "",
        "menu_id": 70111921
      },
      {
        "item_en": "Special Tuna Pizza - Medium",
        "item_ar": "Special Tuna Pizza - Medium",
        "price": 24,
        "currency": "SAR",
        "description": "Delicious thin crust pizza topped with tuna slices and special toppings",
        "image": "https://images.deliveryhero.io/image/hungerstation/product/image_url_ref/15acd1ba53f24546beb49cefb690b37a.jpeg?width=1920",
        "offer_price": null,
        "discount": "",
        "menu_id": 70111936
      },
      {
        "item_en": "Special Plain Cheese Pizza - Medium",
        "item_ar": "Special Plain Cheese Pizza - Medium",
        "price": 25,
        "currency": "SAR",
        "description": "Delicious thin crust pizza topped with cheese and special toppings",
        "image": "https://images.deliveryhero.io/image/hungerstation/product/image_url_ref/b4315f1afc1000e3c8ce0f7011f20abb.jpeg?width=1920",
        "offer_price": null,
        "discount": "",
        "menu_id": 70111948
      },
      {
        "item_en": "Special Chicken Pizza - Medium",
        "item_ar": "Special Chicken Pizza - Medium",
        "price": 23,
        "currency": "SAR",
        "description": "Delicious thin crust pizza topped with chicken slices and special toppings",
        "image": "https://images.deliveryhero.io/image/hungerstation/product/image_url_ref/771821bbff967520442e5ccc6155386e.jpeg?width=1920",
        "offer_price": null,
        "discount": "",
        "menu_id": 70111957
      },
      {
        "item_en": "Regular Vegetable Pizza - Large",
        "item_ar": "Regular Vegetable Pizza - Large",
        "price": 28,
        "currency": "SAR",
        "description": "A delicious thin crust pizza topped with a variety of vegetables.",
        "image": "https://images.deliveryhero.io/image/hungerstation/product/image_url_ref/db83a6957aa418f83fa755d89659506f.jpeg?width=1920",
        "offer_price": null,
        "discount": "",
        "menu_id": 70111910
      },
      {
        "item_en": "Regular Sausage Pizza - Large",
        "item_ar": "Regular Sausage Pizza - Large",
        "price": 28,
        "currency": "SAR",
        "description": "A delicious thin crust pizza topped with sausage slices.",
        "image": "https://images.deliveryhero.io/image/hungerstation/product/image_url_ref/60ce8ea8745826c98590ed3b04fd52a3.jpeg?width=1920",
        "offer_price": null,
        "discount": "",
        "menu_id": 70111916
      },
      {
        "item_en": "Special Pepperoni Pizza - Medium",
        "item_ar": "Special Pepperoni Pizza - Medium",
        "price": 25,
        "currency": "SAR",
        "description": "A delicious thin crust pizza topped with meat slices.",
        "image": "https://images.deliveryhero.io/image/hungerstation/product/image_url_ref/31c6f1b61766f52c4509d6359c72e6d4.jpeg?width=1920",
        "offer_price": null,
        "discount": "",
        "menu_id": 70111924
      },
      {
        "item_en": "Tuna Pizza - Large",
        "item_ar": "Tuna Pizza - Large",
        "price": 28,
        "currency": "SAR",
        "description": "Delicious thin crust pizza topped with tuna slices",
        "image": "https://images.deliveryhero.io/image/hungerstation/product/image_url_ref/411de729b71b6f01c9f78252e9021aad.jpeg?width=1920",
        "offer_price": null,
        "discount": "",
        "menu_id": 70111934
      },
      {
        "item_en": "Plain Cheese Pizza - Large",
        "item_ar": "Plain Cheese Pizza - Large",
        "price": 28,
        "currency": "SAR",
        "description": "Delicious thin crust pizza topped with cheese",
        "image": "https://images.deliveryhero.io/image/hungerstation/product/image_url_ref/93daa66809f17f47a70112e78e123286.jpeg?width=1920",
        "offer_price": null,
        "discount": "",
        "menu_id": 70111946
      },
      {
        "item_en": "Ash Albulbul - Large",
        "item_ar": "Ash Albulbul - Large",
        "price": 28,
        "currency": "SAR",
        "description": "Delicious thin crust pizza topped with cheese and honey",
        "image": "https://images.deliveryhero.io/image/hungerstation/product/image_url_ref/62f089438abaac1256951ff534ca1d7c.jpeg?width=1920",
        "offer_price": null,
        "discount": "",
        "menu_id": 70111952
      },
      {
        "item_en": "Chicken Pizza - Large",
        "item_ar": "Chicken Pizza - Large",
        "price": 28,
        "currency": "SAR",
        "description": "Delicious thin crust pizza topped with chicken slices",
        "image": "https://images.deliveryhero.io/image/hungerstation/product/image_url_ref/145360314e36f146c11ac45ef71f6d5a.jpeg?width=1920",
        "offer_price": null,
        "discount": "",
        "menu_id": 70111955
      },
      {
        "item_en": "Layered Pizza - Large",
        "item_ar": "Layered Pizza - Large",
        "price": 28,
        "currency": "SAR",
        "description": "A pizza rich with multiple layers of cheese, sauce, and a variety of toppings, combining flavors in every bite.",
        "image": "https://images.deliveryhero.io/image/hungerstation/product/image_url_ref/a628f3fa0d763d02312373867dfd3f51.jpeg?width=1920",
        "offer_price": null,
        "discount": "",
        "menu_id": 70111907
      },
      {
        "item_en": "Special Vegetable Pizza - Large",
        "item_ar": "Special Vegetable Pizza - Large",
        "price": 28,
        "currency": "SAR",
        "description": "A delicious thin crust pizza topped with vegetables and special toppings.",
        "image": "https://images.deliveryhero.io/image/hungerstation/product/image_url_ref/20d7e6d8215fd178831bb8305ac82dde.jpeg?width=1920",
        "offer_price": null,
        "discount": "",
        "menu_id": 70111913
      },
      {
        "item_en": "Special Sausage Pizza - Large",
        "item_ar": "Special Sausage Pizza - Large",
        "price": 30,
        "currency": "SAR",
        "description": "A delicious thin crust pizza topped with sausage slices and special toppings.",
        "image": "https://images.deliveryhero.io/image/hungerstation/product/image_url_ref/0d2db9b53bd17fdbe5708075c8f61d5d.jpeg?width=1920",
        "offer_price": null,
        "discount": "",
        "menu_id": 70111919
      },
      {
        "item_en": "Pepperoni Pizza - Large",
        "item_ar": "Pepperoni Pizza - Large",
        "price": 30,
        "currency": "SAR",
        "description": "A delicious pizza prepared in our own way with pepperoni.",
        "image": "https://images.deliveryhero.io/image/hungerstation/product/image_url_ref/365ca3429d276f14ffede85013498fa4.jpeg?width=1920",
        "offer_price": null,
        "discount": "",
        "menu_id": 70111922
      },
      {
        "item_en": "Special Tuna Pizza - Large",
        "item_ar": "Special Tuna Pizza - Large",
        "price": 30,
        "currency": "SAR",
        "description": "Delicious thin crust pizza topped with tuna slices and special toppings",
        "image": "https://images.deliveryhero.io/image/hungerstation/product/image_url_ref/15acd1ba53f24546beb49cefb690b37a.jpeg?width=1920",
        "offer_price": null,
        "discount": "",
        "menu_id": 70111937
      },
      {
        "item_en": "Special Plain Cheese Pizza - Large",
        "item_ar": "Special Plain Cheese Pizza - Large",
        "price": 30,
        "currency": "SAR",
        "description": "Delicious thin crust pizza topped with cheese and special toppings",
        "image": "https://images.deliveryhero.io/image/hungerstation/product/image_url_ref/b4315f1afc1000e3c8ce0f7011f20abb.jpeg?width=1920",
        "offer_price": null,
        "discount": "",
        "menu_id": 70111949
      },
      {
        "item_en": "Special Chicken Pizza - Large",
        "item_ar": "Special Chicken Pizza - Large",
        "price": 28,
        "currency": "SAR",
        "description": "Delicious thin crust pizza topped with chicken slices and special toppings",
        "image": "https://images.deliveryhero.io/image/hungerstation/product/image_url_ref/771821bbff967520442e5ccc6155386e.jpeg?width=1920",
        "offer_price": null,
        "discount": "",
        "menu_id": 70111958
      },
      {
        "item_en": "Special Pepperoni Pizza - Large",
        "item_ar": "Special Pepperoni Pizza - Large",
        "price": 30,
        "currency": "SAR",
        "description": "A delicious thin crust pizza topped with meat slices.",
        "image": "https://images.deliveryhero.io/image/hungerstation/product/image_url_ref/31c6f1b61766f52c4509d6359c72e6d4.jpeg?width=1920",
        "offer_price": null,
        "discount": "",
        "menu_id": 70111925
      }
    ],
    "Breakfast": [
      {
        "item_en": "Fried Eggs Plate",
        "item_ar": "Fried Eggs Plate",
        "price": 7,
        "currency": "SAR",
        "description": "Fried eggs with a golden coating, offering a simple yet delicious taste.",
        "image": "https://images.deliveryhero.io/image/hungerstation/menuitem/image_url_ref/81b14bc90b965dd4f65dd317390c86a8.jpeg?width=222",
        "offer_price": null,
        "discount": "",
        "menu_id": 70111864
      },
      {
        "item_en": "Shakshouka",
        "item_ar": "Shakshouka",
        "price": 13,
        "currency": "SAR",
        "description": "A traditional dish consisting of eggs cooked with tomatoes and special spices.",
        "image": "https://images.deliveryhero.io/image/hungerstation/menuitem/image_url_ref/fa00d0fa6ad17ca09d7c76d858f9b86c.jpeg?width=222",
        "offer_price": null,
        "discount": "",
        "menu_id": 70111865
      },
      {
        "item_en": "Tuna Plate",
        "item_ar": "Tuna Plate",
        "price": 18,
        "currency": "SAR",
        "description": "A light and tasty tuna bowl served with fresh veggies and a touch of olive oil — perfect for a quick and healthy bite",
        "image": "https://images.deliveryhero.io/image/hungerstation/menuitem/image_url_ref/db58f944e9289c6894ec440d61947a15.jpeg?width=222",
        "offer_price": null,
        "discount": "",
        "menu_id": 70111869
      }
    ],
    "Sandwiches": [
      {
        "item_en": "Egg Burger",
        "item_ar": "Egg Burger",
        "price": 14,
        "currency": "SAR",
        "description": "A burger sandwich stuffed with a delicious egg slice",
        "image": "https://images.deliveryhero.io/image/hungerstation/menuitem/image_url_ref/e417fb2a3ac1d41062c118957b6701a0.jpeg?width=222",
        "offer_price": null,
        "discount": "",
        "menu_id": 70111879
      },
      {
        "item_en": "Chicken Burger - Regular",
        "item_ar": "Chicken Burger - Regular",
        "price": 15,
        "currency": "SAR",
        "description": "A burger sandwich stuffed with a chicken patty, special burger sauce, and delicious fresh vegetables.",
        "image": "https://images.deliveryhero.io/image/hungerstation/product/image_url_ref/233d4ac82cef59041bc0300d70403466.jpeg?width=1920",
        "offer_price": null,
        "discount": "",
        "menu_id": 70111870
      },
      {
        "item_en": "Chicken Burger - Double",
        "item_ar": "Chicken Burger - Double",
        "price": 18,
        "currency": "SAR",
        "description": "A burger sandwich stuffed with a chicken patty, special burger sauce, and delicious fresh vegetables.",
        "image": "https://images.deliveryhero.io/image/hungerstation/product/image_url_ref/233d4ac82cef59041bc0300d70403466.jpeg?width=1920",
        "offer_price": null,
        "discount": "",
        "menu_id": 70111871
      },
      {
        "item_en": "Chicken Burger - Meal",
        "item_ar": "Chicken Burger - Meal",
        "price": 28,
        "currency": "SAR",
        "description": "A burger sandwich stuffed with a chicken patty, special burger sauce, and delicious fresh vegetables.",
        "image": "https://images.deliveryhero.io/image/hungerstation/product/image_url_ref/233d4ac82cef59041bc0300d70403466.jpeg?width=1920",
        "offer_price": null,
        "discount": "",
        "menu_id": 70111872
      }
    ],
    "Falafel": [
      {
        "item_en": "Falafel Saba Oven",
        "item_ar": "Falafel Saba Oven",
        "price": 12,
        "currency": "SAR",
        "description": "Healthy and delicious oven baked falafel",
        "image": "https://images.deliveryhero.io/image/hungerstation/menuitem/image_url_ref/8360eb5f7fee0bb3466121a9e96bdaba.jpeg?width=222",
        "offer_price": null,
        "discount": "",
        "menu_id": 70111974
      },
      {
        "item_en": "Shami Falafel",
        "item_ar": "Shami Falafel",
        "price": 7,
        "currency": "SAR",
        "description": "Fried falafel, crispy on the outside and soft on the inside",
        "image": "https://images.deliveryhero.io/image/global-menu-service/HS_SA/vendor/150519/PRODUCT/70111975/2f8637c3-a66f-41d2-8916-7d0732440510.jpg?width=222",
        "offer_price": null,
        "discount": "",
        "menu_id": 70111975
      },
      {
        "item_en": "Mixed Falafel",
        "item_ar": "Mixed Falafel",
        "price": 8,
        "currency": "SAR",
        "description": "Fried mixed falafel, crispy on the outside and soft on the inside",
        "image": "https://images.deliveryhero.io/image/global-menu-service/HS_SA/vendor/150519/PRODUCT/70111976/8b76b1e1-75e9-4bc5-a463-ace20535df40.jpg?width=222",
        "offer_price": null,
        "discount": "",
        "menu_id": 70111976
      },
      {
        "item_en": "Falafel Plate - Small",
        "item_ar": "Falafel Plate - Small",
        "price": 15,
        "currency": "SAR",
        "description": "Fried falafel, crispy on the outside and soft on the inside",
        "image": "",
        "offer_price": null,
        "discount": "",
        "menu_id": 70111971
      },
      {
        "item_en": "Falafel Plate - Medium",
        "item_ar": "Falafel Plate - Medium",
        "price": 20,
        "currency": "SAR",
        "description": "Fried falafel, crispy on the outside and soft on the inside",
        "image": "",
        "offer_price": null,
        "discount": "",
        "menu_id": 70111972
      },
      {
        "item_en": "Falafel Plate - Large",
        "item_ar": "Falafel Plate - Large",
        "price": 30,
        "currency": "SAR",
        "description": "Fried falafel, crispy on the outside and soft on the inside",
        "image": "",
        "offer_price": null,
        "discount": "",
        "menu_id": 70111973
      }
    ],
    "Side Orders": [
      {
        "item_en": "Hummus - Small",
        "item_ar": "Hummus - Small",
        "price": 12,
        "currency": "SAR",
        "description": "A mixture of mashed chickpeas, olive oil, lemon juice, spices, and tahini.",
        "image": "https://images.deliveryhero.io/image/hungerstation/product/image_url_ref/998e6b292085eac7b3e0d7a97dbfe66b.jpeg?width=1920",
        "offer_price": null,
        "discount": "",
        "menu_id": 70111977
      },
      {
        "item_en": "Mixed Salad - Small",
        "item_ar": "Mixed Salad - Small",
        "price": 13,
        "currency": "SAR",
        "description": "A salad made with fresh chopped vegetables.",
        "image": "https://images.deliveryhero.io/image/hungerstation/product/image_url_ref/433afd94e3ea82a4b9f4efdac581b0f3.jpeg?width=1920",
        "offer_price": null,
        "discount": "",
        "menu_id": 70111979
      },
      {
        "item_en": "Hummus - Big",
        "item_ar": "Hummus - Big",
        "price": 17,
        "currency": "SAR",
        "description": "A mixture of mashed chickpeas, olive oil, lemon juice, spices, and tahini.",
        "image": "https://images.deliveryhero.io/image/hungerstation/product/image_url_ref/998e6b292085eac7b3e0d7a97dbfe66b.jpeg?width=1920",
        "offer_price": null,
        "discount": "",
        "menu_id": 70111978
      },
      {
        "item_en": "Mixed Salad - Big",
        "item_ar": "Mixed Salad - Big",
        "price": 18,
        "currency": "SAR",
        "description": "A salad made with fresh chopped vegetables.",
        "image": "https://images.deliveryhero.io/image/hungerstation/product/image_url_ref/433afd94e3ea82a4b9f4efdac581b0f3.jpeg?width=1920",
        "offer_price": null,
        "discount": "",
        "menu_id": 70111980
      }
    ],
    "Fresh Juices": [
      {
        "item_en": "Mango - Small",
        "item_ar": "Mango - Small",
        "price": 8,
        "currency": "SAR",
        "description": "Refreshing fresh mango juice",
        "image": "https://images.deliveryhero.io/image/hungerstation/product/image_url_ref/d42ea13add41c5ddb5bbac649c2f8c95.jpeg?width=1920",
        "offer_price": null,
        "discount": "",
        "menu_id": 70111985
      },
      {
        "item_en": "Guava - Small",
        "item_ar": "Guava - Small",
        "price": 8,
        "currency": "SAR",
        "description": "Refreshing fresh guava juice",
        "image": "https://images.deliveryhero.io/image/hungerstation/product/image_url_ref/428af89081d70880466221500eb3855d.jpeg?width=1920",
        "offer_price": null,
        "discount": "",
        "menu_id": 70111989
      },
      {
        "item_en": "Strawberry Milk - Small",
        "item_ar": "Strawberry Milk - Small",
        "price": 8,
        "currency": "SAR",
        "description": "Refreshing fresh strawberry milk juice",
        "image": "https://images.deliveryhero.io/image/hungerstation/product/image_url_ref/955b30dc46e160342dd6f66f9bc3fb20.jpeg?width=1920",
        "offer_price": null,
        "discount": "",
        "menu_id": 70111993
      },
      {
        "item_en": "Cocktail - Small",
        "item_ar": "Cocktail - Small",
        "price": 8,
        "currency": "SAR",
        "description": "Refreshing fresh fruit juice",
        "image": "https://images.deliveryhero.io/image/hungerstation/product/image_url_ref/0e0d9e9d659a4bfbd80fe6672295beac.jpeg?width=1920",
        "offer_price": null,
        "discount": "",
        "menu_id": 70111997
      },
      {
        "item_en": "Banana Apple Milk - Small",
        "item_ar": "Banana Apple Milk - Small",
        "price": 8,
        "currency": "SAR",
        "description": "Refreshing fresh milk, apple, and banana juice",
        "image": "https://images.deliveryhero.io/image/hungerstation/product/image_url_ref/1f0051bb1865013bffb2addbe6408988.jpeg?width=1920",
        "offer_price": null,
        "discount": "",
        "menu_id": 70112009
      },
      {
        "item_en": "Apple Orange - Small",
        "item_ar": "Apple Orange - Small",
        "price": 8,
        "currency": "SAR",
        "description": "Refreshing fresh apple and orange juice",
        "image": "https://images.deliveryhero.io/image/hungerstation/product/image_url_ref/3c74f82b0c986aaeb9f47578996fcbca.jpeg?width=1920",
        "offer_price": null,
        "discount": "",
        "menu_id": 70112013
      },
      {
        "item_en": "Mango Milk - Small",
        "item_ar": "Mango Milk - Small",
        "price": 8,
        "currency": "SAR",
        "description": "Refreshing fresh milk and mango juice",
        "image": "https://images.deliveryhero.io/image/hungerstation/product/image_url_ref/cc0b3de02af277a4890baaaed19c642b.jpeg?width=1920",
        "offer_price": null,
        "discount": "",
        "menu_id": 70112021
      },
      {
        "item_en": "Lemon Mint - Small",
        "item_ar": "Lemon Mint - Small",
        "price": 8,
        "currency": "SAR",
        "description": "Refreshing fresh mint and lemon juice",
        "image": "https://images.deliveryhero.io/image/hungerstation/product/image_url_ref/ff061f083d8774863f9ff2ca7fd2dcfa.jpeg?width=1920",
        "offer_price": null,
        "discount": "",
        "menu_id": 70112025
      },
      {
        "item_en": "Lemon - Small",
        "item_ar": "Lemon - Small",
        "price": 8,
        "currency": "SAR",
        "description": "Refreshing fresh lime juice",
        "image": "https://images.deliveryhero.io/image/hungerstation/product/image_url_ref/5374ae381f6b5b161259c3fc21f79241.jpeg?width=1920",
        "offer_price": null,
        "discount": "",
        "menu_id": 70112029
      },
      {
        "item_en": "Banana Milk - Small",
        "item_ar": "Banana Milk - Small",
        "price": 8,
        "currency": "SAR",
        "description": "Refreshing fresh milk and banana juice",
        "image": "https://images.deliveryhero.io/image/hungerstation/product/image_url_ref/dd0c2c3cf0c62e109daf7e3ed7d11e2c.jpeg?width=1920",
        "offer_price": null,
        "discount": "",
        "menu_id": 70112041
      },
      {
        "item_en": "Asfahany - Big",
        "item_ar": "Asfahany - Big",
        "price": 12,
        "currency": "SAR",
        "description": "Refreshing fresh mango, banana, and special blend juice",
        "image": "https://images.deliveryhero.io/image/hungerstation/product/image_url_ref/9001911711d09e7863a982b46d2c7d77.jpeg?width=1920",
        "offer_price": null,
        "discount": "",
        "menu_id": 70112020
      },
      {
        "item_en": "Mango - Medium",
        "item_ar": "Mango - Medium",
        "price": 12,
        "currency": "SAR",
        "description": "Refreshing fresh mango juice",
        "image": "https://images.deliveryhero.io/image/hungerstation/product/image_url_ref/d42ea13add41c5ddb5bbac649c2f8c95.jpeg?width=1920",
        "offer_price": null,
        "discount": "",
        "menu_id": 70111986
      },
      {
        "item_en": "Guava - Medium",
        "item_ar": "Guava - Medium",
        "price": 12,
        "currency": "SAR",
        "description": "Refreshing fresh guava juice",
        "image": "https://images.deliveryhero.io/image/hungerstation/product/image_url_ref/428af89081d70880466221500eb3855d.jpeg?width=1920",
        "offer_price": null,
        "discount": "",
        "menu_id": 70111990
      },
      {
        "item_en": "Strawberry Milk - Medium",
        "item_ar": "Strawberry Milk - Medium",
        "price": 12,
        "currency": "SAR",
        "description": "Refreshing fresh strawberry milk juice",
        "image": "https://images.deliveryhero.io/image/hungerstation/product/image_url_ref/955b30dc46e160342dd6f66f9bc3fb20.jpeg?width=1920",
        "offer_price": null,
        "discount": "",
        "menu_id": 70111994
      },
      {
        "item_en": "Cocktail - Medium",
        "item_ar": "Cocktail - Medium",
        "price": 12,
        "currency": "SAR",
        "description": "Refreshing fresh fruit juice",
        "image": "https://images.deliveryhero.io/image/hungerstation/product/image_url_ref/0e0d9e9d659a4bfbd80fe6672295beac.jpeg?width=1920",
        "offer_price": null,
        "discount": "",
        "menu_id": 70111998
      },
      {
        "item_en": "Banana Apple Milk - Medium",
        "item_ar": "Banana Apple Milk - Medium",
        "price": 12,
        "currency": "SAR",
        "description": "Refreshing fresh milk, apple, and banana juice",
        "image": "https://images.deliveryhero.io/image/hungerstation/product/image_url_ref/1f0051bb1865013bffb2addbe6408988.jpeg?width=1920",
        "offer_price": null,
        "discount": "",
        "menu_id": 70112010
      },
      {
        "item_en": "Apple Orange - Medium",
        "item_ar": "Apple Orange - Medium",
        "price": 12,
        "currency": "SAR",
        "description": "Refreshing fresh apple and orange juice",
        "image": "https://images.deliveryhero.io/image/hungerstation/product/image_url_ref/3c74f82b0c986aaeb9f47578996fcbca.jpeg?width=1920",
        "offer_price": null,
        "discount": "",
        "menu_id": 70112014
      },
      {
        "item_en": "Mango Milk - Medium",
        "item_ar": "Mango Milk - Medium",
        "price": 12,
        "currency": "SAR",
        "description": "Refreshing fresh milk and mango juice",
        "image": "https://images.deliveryhero.io/image/hungerstation/product/image_url_ref/cc0b3de02af277a4890baaaed19c642b.jpeg?width=1920",
        "offer_price": null,
        "discount": "",
        "menu_id": 70112022
      },
      {
        "item_en": "Lemon Mint - Medium",
        "item_ar": "Lemon Mint - Medium",
        "price": 12,
        "currency": "SAR",
        "description": "Refreshing fresh mint and lemon juice",
        "image": "https://images.deliveryhero.io/image/hungerstation/product/image_url_ref/ff061f083d8774863f9ff2ca7fd2dcfa.jpeg?width=1920",
        "offer_price": null,
        "discount": "",
        "menu_id": 70112026
      },
      {
        "item_en": "Lemon - Medium",
        "item_ar": "Lemon - Medium",
        "price": 12,
        "currency": "SAR",
        "description": "Refreshing fresh lime juice",
        "image": "https://images.deliveryhero.io/image/hungerstation/product/image_url_ref/5374ae381f6b5b161259c3fc21f79241.jpeg?width=1920",
        "offer_price": null,
        "discount": "",
        "menu_id": 70112030
      },
      {
        "item_en": "Banana Milk - Medium",
        "item_ar": "Banana Milk - Medium",
        "price": 12,
        "currency": "SAR",
        "description": "Refreshing fresh milk and banana juice",
        "image": "https://images.deliveryhero.io/image/hungerstation/product/image_url_ref/dd0c2c3cf0c62e109daf7e3ed7d11e2c.jpeg?width=1920",
        "offer_price": null,
        "discount": "",
        "menu_id": 70112042
      },
      {
        "item_en": "Mango - Large",
        "item_ar": "Mango - Large",
        "price": 20,
        "currency": "SAR",
        "description": "Refreshing fresh mango juice",
        "image": "https://images.deliveryhero.io/image/hungerstation/product/image_url_ref/d42ea13add41c5ddb5bbac649c2f8c95.jpeg?width=1920",
        "offer_price": null,
        "discount": "",
        "menu_id": 70111987
      },
      {
        "item_en": "Guava - Large",
        "item_ar": "Guava - Large",
        "price": 20,
        "currency": "SAR",
        "description": "Refreshing fresh guava juice",
        "image": "https://images.deliveryhero.io/image/hungerstation/product/image_url_ref/428af89081d70880466221500eb3855d.jpeg?width=1920",
        "offer_price": null,
        "discount": "",
        "menu_id": 70111991
      },
      {
        "item_en": "Strawberry Milk - Large",
        "item_ar": "Strawberry Milk - Large",
        "price": 20,
        "currency": "SAR",
        "description": "Refreshing fresh strawberry milk juice",
        "image": "https://images.deliveryhero.io/image/hungerstation/product/image_url_ref/955b30dc46e160342dd6f66f9bc3fb20.jpeg?width=1920",
        "offer_price": null,
        "discount": "",
        "menu_id": 70111995
      },
      {
        "item_en": "Cocktail - Large",
        "item_ar": "Cocktail - Large",
        "price": 20,
        "currency": "SAR",
        "description": "Refreshing fresh fruit juice",
        "image": "https://images.deliveryhero.io/image/hungerstation/product/image_url_ref/0e0d9e9d659a4bfbd80fe6672295beac.jpeg?width=1920",
        "offer_price": null,
        "discount": "",
        "menu_id": 70111999
      },
      {
        "item_en": "Banana Apple Milk - Large",
        "item_ar": "Banana Apple Milk - Large",
        "price": 20,
        "currency": "SAR",
        "description": "Refreshing fresh milk, apple, and banana juice",
        "image": "https://images.deliveryhero.io/image/hungerstation/product/image_url_ref/1f0051bb1865013bffb2addbe6408988.jpeg?width=1920",
        "offer_price": null,
        "discount": "",
        "menu_id": 70112011
      },
      {
        "item_en": "Apple Orange - Large",
        "item_ar": "Apple Orange - Large",
        "price": 20,
        "currency": "SAR",
        "description": "Refreshing fresh apple and orange juice",
        "image": "https://images.deliveryhero.io/image/hungerstation/product/image_url_ref/3c74f82b0c986aaeb9f47578996fcbca.jpeg?width=1920",
        "offer_price": null,
        "discount": "",
        "menu_id": 70112015
      },
      {
        "item_en": "Mango Milk - Large",
        "item_ar": "Mango Milk - Large",
        "price": 20,
        "currency": "SAR",
        "description": "Refreshing fresh milk and mango juice",
        "image": "https://images.deliveryhero.io/image/hungerstation/product/image_url_ref/cc0b3de02af277a4890baaaed19c642b.jpeg?width=1920",
        "offer_price": null,
        "discount": "",
        "menu_id": 70112023
      },
      {
        "item_en": "Lemon Mint - Large",
        "item_ar": "Lemon Mint - Large",
        "price": 20,
        "currency": "SAR",
        "description": "Refreshing fresh mint and lemon juice",
        "image": "https://images.deliveryhero.io/image/hungerstation/product/image_url_ref/ff061f083d8774863f9ff2ca7fd2dcfa.jpeg?width=1920",
        "offer_price": null,
        "discount": "",
        "menu_id": 70112027
      },
      {
        "item_en": "Lemon - Large",
        "item_ar": "Lemon - Large",
        "price": 20,
        "currency": "SAR",
        "description": "Refreshing fresh lime juice",
        "image": "https://images.deliveryhero.io/image/hungerstation/product/image_url_ref/5374ae381f6b5b161259c3fc21f79241.jpeg?width=1920",
        "offer_price": null,
        "discount": "",
        "menu_id": 70112031
      },
      {
        "item_en": "Banana Milk - Large",
        "item_ar": "Banana Milk - Large",
        "price": 20,
        "currency": "SAR",
        "description": "Refreshing fresh milk and banana juice",
        "image": "https://images.deliveryhero.io/image/hungerstation/product/image_url_ref/dd0c2c3cf0c62e109daf7e3ed7d11e2c.jpeg?width=1920",
        "offer_price": null,
        "discount": "",
        "menu_id": 70112043
      },
      {
        "item_en": "Mango - Very Large",
        "item_ar": "Mango - Very Large",
        "price": 25,
        "currency": "SAR",
        "description": "Refreshing fresh mango juice",
        "image": "https://images.deliveryhero.io/image/hungerstation/product/image_url_ref/d42ea13add41c5ddb5bbac649c2f8c95.jpeg?width=1920",
        "offer_price": null,
        "discount": "",
        "menu_id": 70111988
      },
      {
        "item_en": "Guava - Very Large",
        "item_ar": "Guava - Very Large",
        "price": 25,
        "currency": "SAR",
        "description": "Refreshing fresh guava juice",
        "image": "https://images.deliveryhero.io/image/hungerstation/product/image_url_ref/428af89081d70880466221500eb3855d.jpeg?width=1920",
        "offer_price": null,
        "discount": "",
        "menu_id": 70111992
      },
      {
        "item_en": "Strawberry Milk - Very Large",
        "item_ar": "Strawberry Milk - Very Large",
        "price": 25,
        "currency": "SAR",
        "description": "Refreshing fresh strawberry milk juice",
        "image": "https://images.deliveryhero.io/image/hungerstation/product/image_url_ref/955b30dc46e160342dd6f66f9bc3fb20.jpeg?width=1920",
        "offer_price": null,
        "discount": "",
        "menu_id": 70111996
      },
      {
        "item_en": "Cocktail - Very Large",
        "item_ar": "Cocktail - Very Large",
        "price": 25,
        "currency": "SAR",
        "description": "Refreshing fresh fruit juice",
        "image": "https://images.deliveryhero.io/image/hungerstation/product/image_url_ref/0e0d9e9d659a4bfbd80fe6672295beac.jpeg?width=1920",
        "offer_price": null,
        "discount": "",
        "menu_id": 70112000
      },
      {
        "item_en": "Banana Apple Milk - Very Large",
        "item_ar": "Banana Apple Milk - Very Large",
        "price": 25,
        "currency": "SAR",
        "description": "Refreshing fresh milk, apple, and banana juice",
        "image": "https://images.deliveryhero.io/image/hungerstation/product/image_url_ref/1f0051bb1865013bffb2addbe6408988.jpeg?width=1920",
        "offer_price": null,
        "discount": "",
        "menu_id": 70112012
      },
      {
        "item_en": "Apple Orange - Very Large",
        "item_ar": "Apple Orange - Very Large",
        "price": 25,
        "currency": "SAR",
        "description": "Refreshing fresh apple and orange juice",
        "image": "https://images.deliveryhero.io/image/hungerstation/product/image_url_ref/3c74f82b0c986aaeb9f47578996fcbca.jpeg?width=1920",
        "offer_price": null,
        "discount": "",
        "menu_id": 70112016
      },
      {
        "item_en": "Mango Milk - Very Large",
        "item_ar": "Mango Milk - Very Large",
        "price": 25,
        "currency": "SAR",
        "description": "Refreshing fresh milk and mango juice",
        "image": "https://images.deliveryhero.io/image/hungerstation/product/image_url_ref/cc0b3de02af277a4890baaaed19c642b.jpeg?width=1920",
        "offer_price": null,
        "discount": "",
        "menu_id": 70112024
      },
      {
        "item_en": "Lemon Mint - Very Large",
        "item_ar": "Lemon Mint - Very Large",
        "price": 25,
        "currency": "SAR",
        "description": "Refreshing fresh mint and lemon juice",
        "image": "https://images.deliveryhero.io/image/hungerstation/product/image_url_ref/ff061f083d8774863f9ff2ca7fd2dcfa.jpeg?width=1920",
        "offer_price": null,
        "discount": "",
        "menu_id": 70112028
      },
      {
        "item_en": "Lemon - Very Large",
        "item_ar": "Lemon - Very Large",
        "price": 25,
        "currency": "SAR",
        "description": "Refreshing fresh lime juice",
        "image": "https://images.deliveryhero.io/image/hungerstation/product/image_url_ref/5374ae381f6b5b161259c3fc21f79241.jpeg?width=1920",
        "offer_price": null,
        "discount": "",
        "menu_id": 70112032
      },
      {
        "item_en": "Banana Milk - Very Large",
        "item_ar": "Banana Milk - Very Large",
        "price": 25,
        "currency": "SAR",
        "description": "Refreshing fresh milk and banana juice",
        "image": "https://images.deliveryhero.io/image/hungerstation/product/image_url_ref/dd0c2c3cf0c62e109daf7e3ed7d11e2c.jpeg?width=1920",
        "offer_price": null,
        "discount": "",
        "menu_id": 70112044
      }
    ]
  },
  "generated_at": "2025-08-05T20:31:20.039Z",
  "source": "Hungerstation"
}